README.md
setup.cfg
setup.py
PYPI_PACKAGE_PRUEBA.egg-info/PKG-INFO
PYPI_PACKAGE_PRUEBA.egg-info/SOURCES.txt
PYPI_PACKAGE_PRUEBA.egg-info/dependency_links.txt
PYPI_PACKAGE_PRUEBA.egg-info/top_level.txt
economyPackage/__init__.py
economyPackage/mathsEconomy/__init__.py
economyPackage/mathsEconomy/myMathsUtil.py
pypi_package_Prueba.egg-info/PKG-INFO
pypi_package_Prueba.egg-info/SOURCES.txt
pypi_package_Prueba.egg-info/dependency_links.txt
pypi_package_Prueba.egg-info/top_level.txt
pypi_package_prueba.egg-info/PKG-INFO
pypi_package_prueba.egg-info/SOURCES.txt
pypi_package_prueba.egg-info/dependency_links.txt
pypi_package_prueba.egg-info/top_level.txt