Metadata-Version: 1.0
Name: PYPI-PACKAGE-PRUEBA
Version: 0.0.7
Summary: Paquete de prueba, clase Python
Home-page: https://github.com/Benjaprogramado/pypi-package-Prueba
Author: Benjamin Schell
Author-email: UNKNOWN
License: GNU
Platform: UNKNOWN
